pyside_migrate/__init__.py
pyside_migrate/cli.py
pyside_migrate/dump.py
pyside_migrate/enum-mappings.json
pyside_migrate/enum_codemod.py
pyside_migrate/type-renames.json
pyside_migrate/type_rename.py
pyside_migrate-0.4.0.dist-info/METADATA
pyside_migrate-0.4.0.dist-info/WHEEL
pyside_migrate-0.4.0.dist-info/entry_points.txt
pyside_migrate-0.4.0.dist-info/RECORD
