Metadata-Version: 2.4
Name: pyside-migrate
Version: 0.4.0
Summary: Command-line tool to migrate PySide2 code to PySide6
Author: Chad Dombrova
License: MIT
Classifier: Development Status :: 3 - Alpha
Classifier: Intended Audience :: Developers
Classifier: License :: OSI Approved :: MIT License
Classifier: Programming Language :: Python :: 3
Classifier: Programming Language :: Python :: 3.10
Classifier: Programming Language :: Python :: 3.11
Classifier: Programming Language :: Python :: 3.12
Classifier: Topic :: Software Development :: Code Generators
Requires-Python: >=3.10
Requires-Dist: libcst>=1.0.0
Provides-Extra: dev
Requires-Dist: pytest>=7.0.0; extra == 'dev'
